{
	"stations": [
		{
			"id": "1",
			"name": "Västerås Auto Experts",
			"address": "23 Erikslundsgatan, Västerås, SE",
			"latitude": 59.621,
			"longitude": 16.5405,
			"phone": "+46 21 555 0101",
			"website": "http://vasterasautoexperts.se",
			"price": 240,
			"description": "Det här är en kort beskrivning på verkstaden. Det här är den bästa verkstaden i Västerås! Välkommen!",
			"image": "https://picsum.photos/seed/daeckad/200"
		},
		{
			"id": "2",
			"name": "Mälaren Car Services",
			"address": "5 Köpmangatan, Västerås, SE",
			"latitude": 59.618,
			"longitude": 16.5545,
			"phone": "+46 21 555 0102",
			"website": "http://malarencarservices.se",
			"price": 460,
			"description": "Det här är en kort beskrivning på verkstaden. Det här är den bästa verkstaden i Västerås! Välkommen!",
			"image": "https://picsum.photos/seed/daeckad/200"
		},
		{
			"id": "3",
			"name": "Västerås Pro Garage",
			"address": "12 Norrbygatan, Västerås, SE",
			"latitude": 59.599,
			"longitude": 16.5055,
			"phone": "+46 21 555 0103",
			"website": "http://vasterasprogarage.se",
			"price": 560,
			"description": "Det här är en kort beskrivning på verkstaden. Det här är den bästa verkstaden i Västerås! Välkommen!",
			"image": "https://picsum.photos/seed/daeckad/200"
		},
		{
			"id": "4",
			"name": "Erikslund Auto Fix",
			"address": "8 Industrigatan, Västerås, SE",
			"latitude": 59.6215,
			"longitude": 16.54,
			"phone": "+46 21 555 0104",
			"website": "http://erikslundautofix.se",
			"price": 290,
			"description": "Det här är en kort beskrivning på verkstaden. Det här är den bästa verkstaden i Västerås! Välkommen!",
			"image": "https://picsum.photos/seed/daeckad/200"
		},
		{
			"id": "5",
			"name": "Car Care Västerås",
			"address": "18 Hantverkargatan, Västerås, SE",
			"latitude": 59.616,
			"longitude": 16.529,
			"phone": "+46 21 555 0105",
			"website": "http://carcarevasteras.se",
			"price": 380,
			"description": "Det här är en kort beskrivning på verkstaden. Det här är den bästa verkstaden i Västerås! Välkommen!",
			"image": "https://picsum.photos/seed/daeckad/200"
		},
		{
			"id": "6",
			"name": "Västerås Fast Service",
			"address": "31 Östermalmsgatan, Västerås, SE",
			"latitude": 59.603,
			"longitude": 16.545,
			"phone": "+46 21 555 0106",
			"website": "http://vasterasfastservice.se",
			"price": 520,
			"description": "Det här är en kort beskrivning på verkstaden. Det här är den bästa verkstaden i Västerås! Välkommen!",
			"image": "https://picsum.photos/seed/daeckad/200"
		},
		{
			"id": "7",
			"name": "Bilreparationer Västerås",
			"address": "44 Järnvägsgatan, Västerås, SE",
			"latitude": 59.609,
			"longitude": 16.5305,
			"phone": "+46 21 555 0107",
			"website": "http://bilreparationervasteras.se",
			"price": 400,
			"description": "Det här är en kort beskrivning på verkstaden. Det här är den bästa verkstaden i Västerås! Välkommen!",
			"image": "https://picsum.photos/seed/daeckad/200"
		},
		{
			"id": "8",
			"name": "Mälarstaden Auto",
			"address": "10 Karlsgatan, Västerås, SE",
			"latitude": 59.6115,
			"longitude": 16.537,
			"phone": "+46 21 555 0108",
			"website": "http://malarstadenauto.se",
			"price": 570,
			"description": "Det här är en kort beskrivning på verkstaden. Det här är den bästa verkstaden i Västerås! Välkommen!",
			"image": "https://picsum.photos/seed/daeckad/200"
		},
		{
			"id": "9",
			"name": "WestTech Motors",
			"address": "7 Östra Ringvägen, Västerås, SE",
			"latitude": 59.6038,
			"longitude": 16.5295,
			"phone": "+46 21 555 0109",
			"website": "http://westtechmotors.se",
			"price": 320,
			"description": "Det här är en kort beskrivning på verkstaden. Det här är den bästa verkstaden i Västerås! Välkommen!",
			"image": "https://picsum.photos/seed/daeckad/200"
		},
		{
			"id": "10",
			"name": "Autocenter Västerås",
			"address": "23 Västra Hamngatan, Västerås, SE",
			"latitude": 59.6201,
			"longitude": 16.5512,
			"phone": "+46 21 555 0110",
			"website": "http://autocentervasteras.se",
			"price": 470,
			"description": "Det här är en kort beskrivning på verkstaden. Det här är den bästa verkstaden i Västerås! Välkommen!",
			"image": "https://picsum.photos/seed/daeckad/200"
		},
		{
			"id": "11",
			"name": "Västerås Express Auto",
			"address": "9 Bergsgatan, Västerås, SE",
			"latitude": 59.607,
			"longitude": 16.5251,
			"phone": "+46 21 555 0111",
			"website": "http://vasterasexpressauto.se",
			"price": 330,
			"description": "Det här är en kort beskrivning på verkstaden. Det här är den bästa verkstaden i Västerås! Välkommen!",
			"image": "https://picsum.photos/seed/daeckad/200"
		},
		{
			"id": "12",
			"name": "Västerås Bilfix",
			"address": "14 Vasagatan, Västerås, SE",
			"latitude": 59.6134,
			"longitude": 16.5419,
			"phone": "+46 21 555 0112",
			"website": "http://vasterasbilfix.se",
			"price": 560,
			"description": "Det här är en kort beskrivning på verkstaden. Det här är den bästa verkstaden i Västerås! Välkommen!",
			"image": "https://picsum.photos/seed/daeckad/200"
		},
		{
			"id": "13",
			"name": "Car Masters Västerås",
			"address": "22 Långgatan, Västerås, SE",
			"latitude": 59.6085,
			"longitude": 16.5421,
			"phone": "+46 21 555 0113",
			"website": "http://carmastersvasteras.se",
			"price": 210,
			"description": "Det här är en kort beskrivning på verkstaden. Det här är den bästa verkstaden i Västerås! Välkommen!",
			"image": "https://picsum.photos/seed/daeckad/200"
		},
		{
			"id": "14",
			"name": "Västerås Speedy Repairs",
			"address": "5 Slottsgatan, Västerås, SE",
			"latitude": 59.6145,
			"longitude": 16.5432,
			"phone": "+46 21 555 0114",
			"website": "http://vasterasspeedyrepairs.se",
			"price": 490,
			"description": "Det här är en kort beskrivning på verkstaden. Det här är den bästa verkstaden i Västerås! Välkommen!",
			"image": "https://picsum.photos/seed/daeckad/200"
		},
		{
			"id": "15",
			"name": "Erikslund Auto Solutions",
			"address": "18 Fabriksgatan, Västerås, SE",
			"latitude": 59.6205,
			"longitude": 16.5325,
			"phone": "+46 21 555 0115",
			"website": "http://erikslundautosolutions.se",
			"price": 430,
			"description": "Det här är en kort beskrivning på verkstaden. Det här är den bästa verkstaden i Västerås! Välkommen!",
			"image": "https://picsum.photos/seed/daeckad/200"
		},
		{
			"id": "16",
			"name": "Västerås ProFix Garage",
			"address": "27 Skultunavägen, Västerås, SE",
			"latitude": 59.6045,
			"longitude": 16.535,
			"phone": "+46 21 555 0116",
			"website": "http://vasterasprofixgarage.se",
			"price": 370,
			"description": "Det här är en kort beskrivning på verkstaden. Det här är den bästa verkstaden i Västerås! Välkommen!",
			"image": "https://picsum.photos/seed/daeckad/200"
		},
		{
			"id": "17",
			"name": "MälarTech Motors",
			"address": "8 Gjutargatan, Västerås, SE",
			"latitude": 59.6052,
			"longitude": 16.5409,
			"phone": "+46 21 555 0117",
			"website": "http://malartechmotors.se",
			"price": 510,
			"description": "Det här är en kort beskrivning på verkstaden. Det här är den bästa verkstaden i Västerås! Välkommen!",
			"image": "https://picsum.photos/seed/daeckad/200"
		},
		{
			"id": "18",
			"name": "Autoworks Västerås",
			"address": "31 Vasagatan, Västerås, SE",
			"latitude": 59.614,
			"longitude": 16.546,
			"phone": "+46 21 555 0118",
			"website": "http://autoworksvasteras.se",
			"price": 430,
			"description": "Det här är en kort beskrivning på verkstaden. Det här är den bästa verkstaden i Västerås! Välkommen!",
			"image": "https://picsum.photos/seed/daeckad/200"
		},
		{
			"id": "19",
			"name": "Västerås Smart Repairs",
			"address": "14 Södra Ringvägen, Västerås, SE",
			"latitude": 59.6105,
			"longitude": 16.52,
			"phone": "+46 21 555 0119",
			"website": "http://vasterassmartrepairs.se",
			"price": 250,
			"description": "Det här är en kort beskrivning på verkstaden. Det här är den bästa verkstaden i Västerås! Välkommen!",
			"image": "https://picsum.photos/seed/daeckad/200"
		},
		{
			"id": "20",
			"name": "Västerås Car Clinic",
			"address": "12 Östra Gatan, Västerås, SE",
			"latitude": 59.605,
			"longitude": 16.5492,
			"phone": "+46 21 555 0120",
			"website": "http://vasterascarclinic.se",
			"price": 300,
			"description": "Det här är en kort beskrivning på verkstaden. Det här är den bästa verkstaden i Västerås! Välkommen!",
			"image": "https://picsum.photos/seed/daeckad/200"
		},
		{
			"id": "21",
			"name": "Bilakuten Västerås",
			"address": "6 Lillåudden, Västerås, SE",
			"latitude": 59.6168,
			"longitude": 16.5551,
			"phone": "+46 21 555 0121",
			"website": "http://bilakutenvasteras.se",
			"price": 590,
			"description": "Det här är en kort beskrivning på verkstaden. Det här är den bästa verkstaden i Västerås! Välkommen!",
			"image": "https://picsum.photos/seed/daeckad/200"
		},
		{
			"id": "22",
			"name": "CarPros Västerås",
			"address": "45 Hälla Vägen, Västerås, SE",
			"latitude": 59.6091,
			"longitude": 16.5581,
			"phone": "+46 21 555 0122",
			"website": "http://carprosvasteras.se",
			"price": 290,
			"description": "Det här är en kort beskrivning på verkstaden. Det här är den bästa verkstaden i Västerås! Välkommen!",
			"image": "https://picsum.photos/seed/daeckad/200"
		},
		{
			"id": "23",
			"name": "MälarCity AutoCare",
			"address": "9 Pilgatan, Västerås, SE",
			"latitude": 59.6172,
			"longitude": 16.5239,
			"phone": "+46 21 555 0123",
			"website": "http://malarcityautocare.se",
			"price": 480,
			"description": "Det här är en kort beskrivning på verkstaden. Det här är den bästa verkstaden i Västerås! Välkommen!",
			"image": "https://picsum.photos/seed/daeckad/200"
		},
		{
			"id": "24",
			"name": "Västerås AutoCheck",
			"address": "12 Fiskartorget, Västerås, SE",
			"latitude": 59.6193,
			"longitude": 16.5478,
			"phone": "+46 21 555 0124",
			"website": "http://vasterasautocheck.se",
			"price": 330,
			"description": "Det här är en kort beskrivning på verkstaden. Det här är den bästa verkstaden i Västerås! Välkommen!",
			"image": "https://picsum.photos/seed/daeckad/200"
		},
		{
			"id": "25",
			"name": "Västerås Car Experts",
			"address": "7 Emausgatan, Västerås, SE",
			"latitude": 59.618,
			"longitude": 16.552,
			"phone": "+46 21 555 0125",
			"website": "http://vasterascarexperts.se",
			"price": 530,
			"description": "Det här är en kort beskrivning på verkstaden. Det här är den bästa verkstaden i Västerås! Välkommen!",
			"image": "https://picsum.photos/seed/daeckad/200"
		},
		{
			"id": "26",
			"name": "Central Bilservice",
			"address": "9 Köpingsvägen, Västerås, SE",
			"latitude": 59.6062,
			"longitude": 16.5433,
			"phone": "+46 21 555 0126",
			"website": "http://centralbilservice.se",
			"price": 260,
			"description": "Det här är en kort beskrivning på verkstaden. Det här är den bästa verkstaden i Västerås! Välkommen!",
			"image": "https://picsum.photos/seed/daeckad/200"
		},
		{
			"id": "27",
			"name": "Autoshop Västerås",
			"address": "2 Bergsmansvägen, Västerås, SE",
			"latitude": 59.6033,
			"longitude": 16.5587,
			"phone": "+46 21 555 0127",
			"website": "http://autoshopvasteras.se",
			"price": 580,
			"description": "Det här är en kort beskrivning på verkstaden. Det här är den bästa verkstaden i Västerås! Välkommen!",
			"image": "https://picsum.photos/seed/daeckad/200"
		},
		{
			"id": "28",
			"name": "Mälarfix Garage",
			"address": "4 Stohagsvägen, Västerås, SE",
			"latitude": 59.6165,
			"longitude": 16.515,
			"phone": "+46 21 555 0128",
			"website": "http://malarfixgarage.se",
			"price": 300,
			"description": "Det här är en kort beskrivning på verkstaden. Det här är den bästa verkstaden i Västerås! Välkommen!",
			"image": "https://picsum.photos/seed/daeckad/200"
		},
		{
			"id": "29",
			"name": "Bilteam Västerås",
			"address": "3 Bäckbyvägen, Västerås, SE",
			"latitude": 59.6121,
			"longitude": 16.54,
			"phone": "+46 21 555 0129",
			"website": "http://bilteamvasteras.se",
			"price": 350,
			"description": "Det här är en kort beskrivning på verkstaden. Det här är den bästa verkstaden i Västerås! Välkommen!",
			"image": "https://picsum.photos/seed/daeckad/200"
		},
		{
			"id": "30",
			"name": "Västerås Auto Diagnostics",
			"address": "18 Köpingsvägen, Västerås, SE",
			"latitude": 59.6153,
			"longitude": 16.554,
			"phone": "+46 21 555 0130",
			"website": "http://vasterasautodiagnostics.se",
			"price": 600,
			"description": "Det här är en kort beskrivning på verkstaden. Det här är den bästa verkstaden i Västerås! Välkommen!",
			"image": "https://picsum.photos/seed/daeckad/200"
		}
	]
}
